jieba_rpc-0.0.4.dist-info/DESCRIPTION.rst
jieba_rpc-0.0.4.dist-info/METADATA
jieba_rpc-0.0.4.dist-info/metadata.json
jieba_rpc-0.0.4.dist-info/RECORD
jieba_rpc-0.0.4.dist-info/top_level.txt
jieba_rpc-0.0.4.dist-info/WHEEL
jiebarpc/__init__.py
jiebarpc/__main__.py
jiebarpc/client.py
jiebarpc/dispatcher.py
jiebarpc/handler.py
jiebarpc/server.py
jiebarpc/utils.py
