Metadata-Version: 2.0
Name: jieba-rpc
Version: 0.0.4
Summary: jieba RPC server
Home-page: https://github.com/messense/jieba-rpc
Author: messense
Author-email: messense@icloud.com
License: UNKNOWN
Keywords: jieba,rpc
Platform: UNKNOWN
Classifier: Development Status :: 4 - Beta
Classifier: License :: OSI Approved :: MIT License
Classifier: Operating System :: MacOS
Classifier: Operating System :: POSIX
Classifier: Operating System :: POSIX :: Linux
Classifier: Programming Language :: Python
Classifier: Programming Language :: Python :: 2.6
Classifier: Programming Language :: Python :: 2.7
Requires-Dist: msgpack-rpc-python
Requires-Dist: six
Requires-Dist: jieba
